ashley/__init__.py
ashley/admin.py
ashley/apps.py
ashley/context_mixins.py
ashley/context_processors.py
ashley/defaults.py
ashley/factories.py
ashley/models.py
ashley/permissions.py
ashley/receivers.py
ashley/urls.py
ashley/validators.py
ashley/views.py
ashley/xapi.py
ashley/api/__init__.py
ashley/api/serializers.py
ashley/api/urls.py
ashley/api/views.py
ashley/auth/__init__.py
ashley/auth/backend.py
ashley/editor/__init__.py
ashley/editor/decorators.py
ashley/editor/widgets.py
ashley/locale/fr_FR/LC_MESSAGES/django.mo
ashley/locale/fr_FR/LC_MESSAGES/django.po
ashley/machina_extensions/__init__.py
ashley/machina_extensions/forum/__init__.py
ashley/machina_extensions/forum/admin.py
ashley/machina_extensions/forum/apps.py
ashley/machina_extensions/forum/factories.py
ashley/machina_extensions/forum/models.py
ashley/machina_extensions/forum/urls.py
ashley/machina_extensions/forum/views.py
ashley/machina_extensions/forum/migrations/0001_initial.py
ashley/machina_extensions/forum/migrations/0002_auto_20150725_0512.py
ashley/machina_extensions/forum/migrations/0003_remove_forum_is_active.py
ashley/machina_extensions/forum/migrations/0004_auto_20170504_2108.py
ashley/machina_extensions/forum/migrations/0005_auto_20170504_2113.py
ashley/machina_extensions/forum/migrations/0006_auto_20170523_2036.py
ashley/machina_extensions/forum/migrations/0007_auto_20170523_2140.py
ashley/machina_extensions/forum/migrations/0008_forum_last_post.py
ashley/machina_extensions/forum/migrations/0009_auto_20170928_2327.py
ashley/machina_extensions/forum/migrations/0010_auto_20181103_1401.py
ashley/machina_extensions/forum/migrations/0011_auto_20190627_2132.py
ashley/machina_extensions/forum/migrations/0012_auto_20200311_1354.py
ashley/machina_extensions/forum/migrations/0013_lti_contexts_and_lti_id.py
ashley/machina_extensions/forum/migrations/0014_auto_20210215_1542.py
ashley/machina_extensions/forum/migrations/0015_auto_20210217_1351.py
ashley-1.3.1.dist-info/LICENSE
ashley-1.3.1.dist-info/METADATA
ashley-1.3.1.dist-info/WHEEL
ashley-1.3.1.dist-info/top_level.txt
ashley-1.3.1.dist-info/zip-safe
ashley-1.3.1.dist-info/RECORD
