Metadata-Version: 2.1
Name: ashley
Version: 1.3.1
Summary: A self-hosted discussion forum for learning
Home-page: https://github.com/openfun/ashley
Author: Open FUN (France Universite Numerique)
Author-email: fun.dev@fun-mooc.fr
License: MIT
Keywords: Django,forum,Open edX,message board,discussion
Platform: UNKNOWN
Classifier: Development Status :: 4 - Beta
Classifier: Framework :: Django
Classifier: Framework :: Django :: 1.11
Classifier: Intended Audience :: Developers
Classifier: License :: OSI Approved :: MIT License
Classifier: Natural Language :: English
Classifier: Programming Language :: Python :: 3
Classifier: Programming Language :: Python :: 3.8
License-File: LICENSE
Requires-Dist: boto3 (==1.22.10)
Requires-Dist: Django (<4,>=3.2.4)
Requires-Dist: django-storages (==1.12.3)
Requires-Dist: django-haystack (==3.2.1)
Requires-Dist: django-lti-toolbox (==1.0.1)
Requires-Dist: django-machina (==1.1.6)
Requires-Dist: draftjs-exporter (==5.0.0)
Requires-Dist: djangorestframework (==3.13.1)
Requires-Dist: elasticsearch (<6.0.0,>=5.0.0)
Requires-Dist: logging-ldp (==0.0.6)
Requires-Dist: oauthlib (>=3.0.0)
Requires-Dist: tincan (==1.0.0)
Provides-Extra: ci
Requires-Dist: twine (==4.0.0) ; extra == 'ci'
Provides-Extra: dev
Requires-Dist: bandit (==1.7.4) ; extra == 'dev'
Requires-Dist: black (==22.3.0) ; extra == 'dev'
Requires-Dist: flake8 (==4.0.1) ; extra == 'dev'
Requires-Dist: ipdb (==0.13.9) ; extra == 'dev'
Requires-Dist: ipython (==8.3.0) ; extra == 'dev'
Requires-Dist: isort (==5.10.1) ; extra == 'dev'
Requires-Dist: mypy (==0.950) ; extra == 'dev'
Requires-Dist: pyfakefs (==4.5.6) ; extra == 'dev'
Requires-Dist: pylint-django (==2.5.3) ; extra == 'dev'
Requires-Dist: pylint (==2.13.8) ; extra == 'dev'
Requires-Dist: pytest-cov (==3.0.0) ; extra == 'dev'
Requires-Dist: pytest-django (==4.5.2) ; extra == 'dev'
Requires-Dist: pytest (==7.1.2) ; extra == 'dev'
Requires-Dist: lxml (==4.8.0) ; extra == 'dev'
Requires-Dist: cssselect (==1.1.0) ; extra == 'dev'
Provides-Extra: sandbox
Requires-Dist: django-configurations (==2.3.2) ; extra == 'sandbox'
Requires-Dist: dockerflow (==2022.1.0) ; extra == 'sandbox'
Requires-Dist: factory-boy (==3.2.1) ; extra == 'sandbox'
Requires-Dist: gunicorn (==20.1.0) ; extra == 'sandbox'
Requires-Dist: psycopg2-binary (==2.9.3) ; extra == 'sandbox'
Requires-Dist: sentry-sdk (==1.5.11) ; extra == 'sandbox'
